rasterra/__init__.py
rasterra/_array.py
rasterra/_features.py
rasterra/_io.py
rasterra/_merge.py
rasterra/_plotting.py
rasterra/_typing.py
rasterra/py.typed
rasterra-0.6.3.dist-info/LICENSE
rasterra-0.6.3.dist-info/METADATA
rasterra-0.6.3.dist-info/WHEEL
rasterra-0.6.3.dist-info/RECORD
