Metadata-Version: 2.3
Name: rasterra
Version: 0.6.3
Summary: A sleek, object-oriented interface designed for intuitive raster data manipulation in Python.
License: BSD-3-Clause
Author: James Collins
Author-email: collijk1@gmail.com
Requires-Python: >=3.12
Classifier: License :: OSI Approved :: BSD License
Classifier: Programming Language :: Python :: 3
Classifier: Programming Language :: Python :: 3.12
Classifier: Programming Language :: Python :: 3.13
Requires-Dist: affine (>=2.4)
Requires-Dist: click (>=8.0)
Requires-Dist: geopandas (>=1.0.1)
Requires-Dist: matplotlib
Requires-Dist: numpy (>=2.0)
Requires-Dist: pyproj (>=3.6.0)
Requires-Dist: rasterio (>=1.3.9)
Requires-Dist: shapely (>=2.0)
Project-URL: Documentation, https://collijk.github.io/rasterra
Project-URL: Homepage, https://collijk.github.io/rasterra
Project-URL: Repository, https://github.com/collijk/rasterra
